cezzis_oauth_fastapi/__init__.py
cezzis_oauth_fastapi/__init__.pyi
cezzis_oauth_fastapi/oauth_authorization.py
cezzis_oauth_fastapi/oauth_authorization.pyi
cezzis_oauth_fastapi/oauth_config.py
cezzis_oauth_fastapi/oauth_config.pyi
cezzis_oauth_fastapi-0.0.25.dist-info/METADATA
cezzis_oauth_fastapi-0.0.25.dist-info/WHEEL
cezzis_oauth_fastapi-0.0.25.dist-info/RECORD
