Metadata-Version: 2.4
Name: cezzis_oauth_fastapi
Version: 0.0.25
Summary: A lightweight, production-ready Python library for OAuth 2.0 authentication. Provides both **token acquisition** and **JWT verification** with enterprise-grade features including automatic token caching, refresh management, JWKS-based verification, and scope validation.
License: MIT
Author: mtnvencenzo
Author-email: rvecchi@gmail.com
Requires-Python: >=3.12,<3.15
Classifier: License :: OSI Approved :: MIT License
Classifier: Programming Language :: Python :: 3
Classifier: Programming Language :: Python :: 3.12
Classifier: Programming Language :: Python :: 3.13
Classifier: Programming Language :: Python :: 3.14
Requires-Dist: authlib (>=1.4.0,<2.0.0)
Requires-Dist: cezzis-oauth (>=0.0.19,<1.0.0)
Requires-Dist: fastapi[standard] (>=0.128.0,<1.0.0)
Requires-Dist: httpx (>=0.28.1,<1.0.0)
Requires-Dist: python-jose[cryptography] (>=3.5.0,<4.0.0)
